delta_kernel_rust_sharing_wrapper-0.3.1.dist-info/METADATA
delta_kernel_rust_sharing_wrapper-0.3.1.dist-info/WHEEL
delta_kernel_rust_sharing_wrapper/__init__.py
delta_kernel_rust_sharing_wrapper/delta_kernel_rust_sharing_wrapper.abi3.so
delta_kernel_rust_sharing_wrapper-0.3.1.dist-info/RECORD
