Metadata-Version: 2.4
Name: delta-kernel-rust-sharing-wrapper
Version: 0.3.1
License: Apache-2.0
